clearskydays/__init__.py
clearskydays/statistics.py
clearskydays-0.0.5.dist-info/LICENSE.txt
clearskydays-0.0.5.dist-info/METADATA
clearskydays-0.0.5.dist-info/WHEEL
clearskydays-0.0.5.dist-info/top_level.txt
clearskydays-0.0.5.dist-info/RECORD
