Metadata-Version: 2.1
Name: clearskydays
Version: 0.0.5
Summary: A simple Python module that determines clear sky days based on solar radiation measurements.
Home-page: 
Author: Abel Delgado Villalba
Author-email: adelgado@pol.una.py
License: MIT
Keywords: clear sky days,solar radiation
Platform: UNKNOWN
Classifier: License :: OSI Approved :: MIT License
Classifier: Programming Language :: Python :: 3
Classifier: Programming Language :: Python :: 3.7
License-File: LICENSE.txt
Requires-Dist: numpy
Requires-Dist: pandas
